Workbook

Sheet Cluster Summary
A1: No. | B1: Main Topic | C1: Cluster Name | D1: Pillar Topic | E1: Total Topics
A2: 1 | B2: Baby, Toddler & Sensory Toys | C2: Activity Walker Toys | D2: push walker toy with activity board | E2: =COUNTIF('All Keywords by Cluster'!$C$2:$C$4933,$C2) -> 24
A3: 2 | B3: Baby, Toddler & Sensory Toys | C3: Age Appropriate Toys | D3: best age appropriate toys for 1 year olds | E3: =COUNTIF('All Keywords by Cluster'!$C$2:$C$4933,$C3) -> 10
A4: 3 | B4: Baby, Toddler & Sensory Toys | C4: Baby Cube Toy | D4: baby cube toy | E4: =COUNTIF('All Keywords by Cluster'!$C$2:$C$4933,$C4) -> 18
A5: 4 | B5: Baby, Toddler & Sensory Toys | C5: Baby Sensory Toys | D5: baby sensory toys | E5: =COUNTIF('All Keywords by Cluster'!$C$2:$C$4933,$C5) -> 19
A6: 5 | B6: Baby, Toddler & Sensory Toys | C6: Baby Toy Development | D6: when do babies start to play with toys | E6: =COUNTIF('All Keywords by Cluster'!$C$2:$C$4933,$C6) -> 16
A7: 6 | B7: Baby, Toddler & Sensory Toys | C7: Bath Toys By Age | D7: best bath toys for 2 year olds top fun and safe picks | E7: =COUNTIF('All Keywords by Cluster'!$C$2:$C$4933,$C7) -> 23
A8: 7 | B8: Baby, Toddler & Sensory Toys | C8: Bath Toys For Age 1 | D8: bath toys for 1 year old | E8: =COUNTIF('All Keywords by Cluster'!$C$2:$C$4933,$C8) -> 21
A9: 8 | B9: Baby, Toddler & Sensory Toys | C9: Car Ride Toys | D9: best toys for the car | E9: =COUNTIF('All Keywords by Cluster'!$C$2:$C$4933,$C9) -> 20
A10: 9 | B10: Baby, Toddler & Sensory Toys | C10: Car Seat Toys For Infants | D10: car seat toys for infants | E10: =COUNTIF('All Keywords by Cluster'!$C$2:$C$4933,$C10) -> 10
A11: 10 | B11: Baby, Toddler & Sensory Toys | C11: DIY Teething Toys | D11: how to make a teething toy diy | E11: =COUNTIF('All Keywords by Cluster'!$C$2:$C$4933,$C11) -> 18
A12: 11 | B12: Baby, Toddler & Sensory Toys | C12: Good Toys For Age 3 | D12: what are good toys for 3 year olds | E12: =COUNTIF('All Keywords by Cluster'!$C$2:$C$4933,$C12) -> 23
A13: 12 | B13: Baby, Toddler & Sensory Toys | C13: Indoor Toys For Age 3 | D13: indoor toys for 3 year old | E13: =COUNTIF('All Keywords by Cluster'!$C$2:$C$4933,$C13) -> 16
... A296: 295 | B296: Toy Care, Shopping & Pet Toys | C296: What Toys Do Guinea Pigs | D296: what toys do guinea pigs like to play with | E296: =COUNTIF('All Keywords by Cluster'!$C$2:$C$4933,$C296) -> 24

Sheet All Keywords by Cluster
A1: No. | B1: Main Topic | C1: Cluster Name | D1: Topic Type | E1: Keyword / Topic | F1: Post URL
A2: 1 | B2: Baby, Toddler & Sensory Toys | C2: Activity Walker Toys | D2: Pillar Topic | E2: push walker toy with activity board | F2: https://funtoykingdom.com/push-walker-toy-with-activity-board/
A3: 2 | B3: Baby, Toddler & Sensory Toys | C3: Activity Walker Toys | D3: Sub-topic | E3: action hero toys | F3: https://funtoykingdom.com/action-hero-toys/
A4: 3 | B4: Baby, Toddler & Sensory Toys | C4: Activity Walker Toys | D4: Sub-topic | E4: addition toy math cubes | F4: https://funtoykingdom.com/addition-toy-math-cubes/
A5: 4 | B5: Baby, Toddler & Sensory Toys | C5: Activity Walker Toys | D5: Sub-topic | E5: augmented reality toy apps | F5: https://funtoykingdom.com/augmented-reality-toy-apps/
A6: 5 | B6: Baby, Toddler & Sensory Toys | C6: Activity Walker Toys | D6: Sub-topic | E6: best push walker toy for hardwood floors | F6: https://funtoykingdom.com/best-push-walker-toy-for-hardwood-floors/
A7: 6 | B7: Baby, Toddler & Sensory Toys | C7: Activity Walker Toys | D7: Sub-topic | E7: biology dissection toy kits | F7: https://funtoykingdom.com/biology-dissection-toy-kits/
A8: 7 | B8: Baby, Toddler & Sensory Toys | C8: Activity Walker Toys | D8: Sub-topic | E8: case ih 1 16 toys | F8: https://funtoykingdom.com/case-ih-1-16-toys/
A9: 8 | B9: Baby, Toddler & Sensory Toys | C9: Activity Walker Toys | D9: Sub-topic | E9: chalk set for sidewalk games | F9: https://funtoykingdom.com/chalk-set-for-sidewalk-games/
A10: 9 | B10: Baby, Toddler & Sensory Toys | C10: Activity Walker Toys | D10: Sub-topic | E10: how to make wooden walking duck toy | F10: https://funtoykingdom.com/how-to-make-wooden-walking-duck-toy/
A11: 10 | B11: Baby, Toddler & Sensory Toys | C11: Activity Walker Toys | D11: Sub-topic | E11: how to paint pull along toy safely | F11: https://funtoykingdom.com/how-to-paint-pull-along-toy-safely/
A12: 11 | B12: Baby, Toddler & Sensory Toys | C12: Activity Walker Toys | D12: Sub-topic | E12: hydraulic toy kits for students | F12: https://funtoykingdom.com/hydraulic-toy-kits-for-students/
A13: 12 | B13: Baby, Toddler & Sensory Toys | C13: Activity Walker Toys | D13: Sub-topic | E13: last action hero toys | F13: https://funtoykingdom.com/last-action-hero-toys/
... A4933: 4932 | B4933: Toy Care, Shopping & Pet Toys | C4933: What Toys Do Guinea Pigs | D4933: Sub-topic | E4933: what toys do huskies like | F4933: https://funtoykingdom.com/what-toys-do-huskies-like/

Sheet Removed Keywords
A1: No. | B1: Keyword | C1: Post URL | D1: Removal Reason | E1: Kept Instead (Duplicate Of)
A2: 1 | B2: 2010 robot dog toy | C2: https://funtoykingdom.com/2010-robot-dog-toy/ | D2: Near-duplicate (cannibalizes another keyword) | E2: toy robot dog 2010
A3: 2 | B3: a drone toy | C3: https://funtoykingdom.com/a-drone-toy/ | D3: Near-duplicate (cannibalizes another keyword) | E3: a toy drone
A4: 3 | B4: a robot toy | C4: https://funtoykingdom.com/a-robot-toy/ | D4: Near-duplicate (cannibalizes another keyword) | E4: a toy robot
A5: 4 | B5: abacus toys | C5: https://funtoykingdom.com/abacus-toys/ | D5: Near-duplicate (cannibalizes another keyword) | E5: what is an abacus toy
A6: 5 | B6: alphabet learning toys | C6: https://funtoykingdom.com/alphabet-learning-toys/ | D6: Near-duplicate (cannibalizes another keyword) | E6: best alphabet learning toys
A7: 6 | B7: angry birds toys set | C7: https://funtoykingdom.com/angry-birds-toys-set/ | D7: Near-duplicate (cannibalizes another keyword) | E7: angry birds toy set
A8: 7 | B8: arpo robot toy | C8: https://funtoykingdom.com/arpo-robot-toy/ | D8: Near-duplicate (cannibalizes another keyword) | E8: arpo the robot toy
A9: 8 | B9: art toys vinyl | C9: https://funtoykingdom.com/art-toys-vinyl/ | D9: Near-duplicate (cannibalizes another keyword) | E9: art of vinyl toys
A10: 9 | B10: art vinyl toys | C10: https://funtoykingdom.com/art-vinyl-toys/ | D10: Near-duplicate (cannibalizes another keyword) | E10: art of vinyl toys
A11: 10 | B11: autism sensory toys | C11: https://funtoykingdom.com/autism-sensory-toys/ | D11: Near-duplicate (cannibalizes another keyword) | E11: what are sensory toys for autism
A12: 11 | B12: baby car seat toy | C12: https://funtoykingdom.com/baby-car-seat-toy/ | D12: Near-duplicate (cannibalizes another keyword) | E12: car seat toys for babies
A13: 12 | B13: baby soft toy blocks | C13: https://funtoykingdom.com/baby-soft-toy-blocks/ | D13: Near-duplicate (cannibalizes another keyword) | E13: soft toy blocks for babies
... A472: 471 | B472: wooden blocks toys | C472: https://funtoykingdom.com/wooden-blocks-toys/ | D472: Near-duplicate (cannibalizes another keyword) | E472: wooden toy blocks
A473: 472 | B473: adult sex toy kit | C473: https://funtoykingdom.com/adult-sex-toy-kit/ | D473: Off-niche: adult sexual product query
A474: 473 | B474: adult toy case | C474: https://funtoykingdom.com/adult-toy-case/ | D474: Off-niche: adult sexual product query
A475: 474 | B475: adult toy kit | C475: https://funtoykingdom.com/adult-toy-kit/ | D475: Off-niche: adult sexual product query
A476: 475 | B476: adult toy kits | C476: https://funtoykingdom.com/adult-toy-kits/ | D476: Off-niche: adult sexual product query
A477: 476 | B477: couples sex toy kit | C477: https://funtoykingdom.com/couples-sex-toy-kit/ | D477: Off-niche: adult sexual product query
A478: 477 | B478: couples sex toy kits | C478: https://funtoykingdom.com/couples-sex-toy-kits/ | D478: Off-niche: adult sexual product query
A479: 478 | B479: sex toy case | C479: https://funtoykingdom.com/sex-toy-case/ | D479: Off-niche: adult sexual product query
A480: 479 | B480: sex toy kit | C480: https://funtoykingdom.com/sex-toy-kit/ | D480: Off-niche: adult sexual product query
A481: 480 | B481: sex toy kits | C481: https://funtoykingdom.com/sex-toy-kits/ | D481: Off-niche: adult sexual product query
A482: 481 | B482: sex toy kits for couples | C482: https://funtoykingdom.com/sex-toy-kits-for-couples/ | D482: Off-niche: adult sexual product query
A483: 482 | B483: sex toy starter kit | C483: https://funtoykingdom.com/sex-toy-starter-kit/ | D483: Off-niche: adult sexual product query
A484: 483 | B484: what can i use to clean my adult toy | C484: https://funtoykingdom.com/what-can-i-use-to-clean-my-adult-toy/ | D484: Off-niche: adult sexual product query
... A742: 741 | B742: toy story video game for kids | C742: https://funtoykingdom.com/toy-story-video-game-for-kids/ | D742: Off-niche: video-game/media query

Sheet Main Topics
A1: No. | B1: Toy Type (Main Topic) | C1: Total Clusters | D1: Total Keywords | E1: What It Covers
A2: 1 | B2: Baby, Toddler & Sensory Toys | C2: =COUNTIF('Cluster Summary'!$B$2:$B$296,$B2) -> 38 | D2: =COUNTIF('All Keywords by Cluster'!$B$2:$B$4933,$B2) -> 669 | E2: Infant and toddler toys, teething, tummy time, bath toys, sensory toys and general age-based toy guides.
A3: 2 | B3: Educational, STEM & Robot Toys | C3: =COUNTIF('Cluster Summary'!$B$2:$B$296,$B3) -> 38 | D3: =COUNTIF('All Keywords by Cluster'!$B$2:$B$4933,$B3) -> 696 | E3: Educational, Montessori and preschool learning toys, STEM and coding kits, robots, electronic and interactive toys, musical toys.
A4: 3 | B4: Cars, Trucks, Trains & RC Toys | C4: =COUNTIF('Cluster Summary'!$B$2:$B$296,$B4) -> 34 | D4: =COUNTIF('All Keywords by Cluster'!$B$2:$B$4933,$B4) -> 549 | E4: Toy cars, diecast and model vehicles, trains and race tracks, RC cars, drones, boats and helicopters.
A5: 4 | B5: Outdoor, Ride-On & Sports Toys | C5: =COUNTIF('Cluster Summary'!$B$2:$B$296,$B5) -> 41 | D5: =COUNTIF('All Keywords by Cluster'!$B$2:$B$4933,$B5) -> 712 | E5: Outdoor toys by age, ride-ons, inflatables and pool toys, sprinklers, climbing and sports toys.
A6: 5 | B6: Dolls, Collectibles & Characters | C6: =COUNTIF('Cluster Summary'!$B$2:$B$296,$B6) -> 35 | D6: =COUNTIF('All Keywords by Cluster'!$B$2:$B$4933,$B6) -> 572 | E6: Dolls and dollhouses, action figures, collectibles, vintage toys, miniatures and franchise toys (Toy Story, Cars, superheroes).
A7: 6 | B7: Pretend Play, Plush & Novelty Toys | C7: =COUNTIF('Cluster Summary'!$B$2:$B$296,$B7) -> 15 | D7: =COUNTIF('All Keywords by Cluster'!$B$2:$B$4933,$B7) -> 300 | E7: Pretend play sets, role-play, plush and stuffed toys, army sets, fidget and capsule novelty toys.
A8: 7 | B8: Building, DIY & Handmade Toys | C8: =COUNTIF('Cluster Summary'!$B$2:$B$296,$B8) -> 43 | D8: =COUNTIF('All Keywords by Cluster'!$B$2:$B$4933,$B8) -> 639 | E8: Building blocks and LEGO, DIY and handmade wooden or cardboard toys, craft and sewing projects.
A9: 8 | B9: Games & Puzzles | C9: =COUNTIF('Cluster Summary'!$B$2:$B$296,$B9) -> 26 | D9: =COUNTIF('All Keywords by Cluster'!$B$2:$B$4933,$B9) -> 408 | E9: Board and card games, party games, jigsaw and wooden puzzles, puzzle care and accessories.
A10: 9 | B10: Toy Care, Shopping & Pet Toys | C10: =COUNTIF('Cluster Summary'!$B$2:$B$296,$B10) -> 25 | D10: =COUNTIF('All Keywords by Cluster'!$B$2:$B$4933,$B10) -> 387 | E10: Buying, selling, donating, cleaning and safety of toys, toy facts, plus dog, cat and small pet toys.
B11: Total | C11: =SUM(C2:C10) -> 295 | D11: =SUM(D2:D10) -> 4932

Sheet Read Me
A1: Label | B1: Detail
A2: Title | B2: Funtoykingdom Keyword Cleanup and Re-Clustering
A3: Source | B3: Original workbook: funtoykingdom keywords.xlsx; sheet used: Posts; columns used: No., Post URL, Keyword. The Posts sheet was the only source.
A4: Total keywords received | B4: 5673
A5: Keywords removed | B5: 741
A6: Keywords kept | B6: 4932
A7: Total clusters | B7: 295
A8: Cluster size guideline | B8: Aim for 8 to 25 keywords per cluster; no cluster exceeds 25.
A9: Clusters below 8 keywords | B9: 0
A10: Reason for clusters below 8 | B10: None. All clusters meet the 8-keyword minimum after relevance filtering and intent-based consolidation.
A11: Cluster naming rules | B11: Unique 2 to 5 word Title Case names; no category prefixes and no hyphen separators; names describe the cluster topic naturally.
A12: Removal: exact duplicates | B12: 0
A13: Removal: near-duplicates | B13: 471
A14: Removal: off-niche | B14: 270
A15: Removal rules | B15: Exact duplicates are identical after case, spacing and punctuation normalization. Near-duplicates share the same search intent and entities and would naturally target one page. Off-niche keywords have an actual intent outside the site's toy topical scope.
A16: Clustering logic | B16: Keywords were re-clustered from scratch using main subject, search intent, entity, subtopic, user problem, content type and semantic similarity. Toy Types were assigned by the keyword's main subject rather than incidental words.
A17: Pillar Topic meaning | B17: The one retained keyword in each cluster that best represents the broad central intent of that cluster and serves as the main page target.
A18: Sub-topic meaning | B18: All other retained keywords in the cluster that support the pillar topic.
A19: Removed Keywords sheet | B19: Every removed keyword appears exactly once with its original URL and removal reason. Duplicate removals also identify the retained keyword in 'Kept Instead'.
A20: Post URLs | B20: Every retained keyword keeps its original Post URL exactly as supplied. No URL was invented, edited or reassigned.
A21: Important exceptions and observations | B21: Ambiguous keywords were generally kept when their intent could reasonably belong to the toy niche. Clear false positives included animal-breed uses of 'toy', adult sexual-product queries, unrelated vehicle or sports equipment, crossword and video-game/media queries, B2B wholesale/distribution, certain local 'near me' queries, and unrelated meanings such as RV 'toy hauler'.
A22: Data limitations | B22: The source contains keywords and Post URLs only; no search-volume, ranking, competition or SERP data was used or claimed.
A23: Total Toy Types (main topics) | B23: 9 (reduced from 28; allowed range 3 to 9). Every cluster sits under exactly one Toy Type. See the Main Topics sheet for cluster and keyword counts per Toy Type.
A24: Toy Type consolidation | B24: Toy Types were regrouped by the main subject of each cluster: (1) baby, toddler and sensory toys, (2) educational, STEM and robot toys, (3) cars, trucks, trains and RC toys, (4) outdoor, ride-on and sports toys, (5) dolls, collectibles and characters, (6) pretend play, plush and novelty toys, (7) building, DIY and handmade toys, (8) games and puzzles, (9) toy care, shopping and pet toys. The former catch-all "General Toys" group was split across these by subject. Cluster names, pillar topics, keywords and Post URLs were not changed; only the Toy Type assignment, sort order and row numbers (No.) were updated.
